MANIFEST.in
README.rst
setup.py
collective/.DS_Store
collective/__init__.py
collective/__init__.pyc
collective.ptg.easyslider.egg-info/PKG-INFO
collective.ptg.easyslider.egg-info/SOURCES.txt
collective.ptg.easyslider.egg-info/dependency_links.txt
collective.ptg.easyslider.egg-info/entry_points.txt
collective.ptg.easyslider.egg-info/namespace_packages.txt
collective.ptg.easyslider.egg-info/not-zip-safe
collective.ptg.easyslider.egg-info/requires.txt
collective.ptg.easyslider.egg-info/top_level.txt
collective/ptg/.DS_Store
collective/ptg/__init__.py
collective/ptg/__init__.pyc
collective/ptg/easyslider/.DS_Store
collective/ptg/easyslider/__init__.py
collective/ptg/easyslider/__init__.pyc
collective/ptg/easyslider/configure.zcml
collective/ptg/easyslider/easyslider.pt
collective/ptg/easyslider/resources/.DS_Store
collective/ptg/easyslider/resources/arrow-left.png
collective/ptg/easyslider/resources/arrow-right.png
collective/ptg/easyslider/resources/arrowl2.gif
collective/ptg/easyslider/resources/arrowr2.gif
collective/ptg/easyslider/resources/bg_body.gif
collective/ptg/easyslider/resources/bg_header.gif
collective/ptg/easyslider/resources/btn_next.gif
collective/ptg/easyslider/resources/btn_prev.gif
collective/ptg/easyslider/resources/button_black_first.png
collective/ptg/easyslider/resources/button_black_last.png
collective/ptg/easyslider/resources/easySlider.css
collective/ptg/easyslider/resources/easySlider.js
collective/ptg/easyslider/resources/greynote.jpg
collective/ptg/easyslider/resources/nextII.gif
collective/ptg/easyslider/resources/no_style.css
collective/ptg/easyslider/resources/pause.png
collective/ptg/easyslider/resources/play.png
collective/ptg/easyslider/resources/prevII.gif
collective/ptg/easyslider/resources/style.css
collective/ptg/easyslider/resources/styleII.css
collective/ptg/easyslider/resources/styleIII.css
collective/ptg/easyslider/resources/styleIV.css
collective/ptg/easyslider/resources/styleV.css
docs/HISTORY.txt
docs/INSTALL.txt
docs/LICENSE.GPL
docs/LICENSE.txt