Metadata-Version: 1.0
Name: collective.ptg.easyslider
Version: 0.3.3.1
Summary: Easyslider gallery type for plonetruegallery
Home-page: https://github.com/medialog/collective.ptg.easyslider
Author: Espen Moe-Nilssen
Author-email: espen@medialog.no
License: GPL
Keywords: plonetruegaller gallery plone addon easyslider
Platform: UNKNOWN
Classifier: Framework :: Plone
Classifier: Programming Language :: Python
